setup.py
llmchat/__init__.py
llmchat/protocol.py
llmchat/version.py
llmchat.egg-info/PKG-INFO
llmchat.egg-info/SOURCES.txt
llmchat.egg-info/dependency_links.txt
llmchat.egg-info/requires.txt
llmchat.egg-info/top_level.txt
llmchat/chat/__init__.py
llmchat/chat/chatglm_6b.py
llmchat/chat/stream_chat.py
llmchat/extras/__init__.py
llmchat/extras/constants.py
llmchat/extras/misc.py
llmchat/extras/template.py
llmchat/hparams/__init__.py
llmchat/hparams/generating_args.py